xps_lib/XPS_ROACH2_base/pcores/opb_adc5g_controller_v1_00_a/hdl/verilog/opb_adc5g_controller.v
/*
 
 Modified version of: 
 XPS_ROACH2_BASE/pcores/opb_katcontroller/hdl/verilog/opb_katcontroller.v
 
 Modified by Rurik Primiani on Feb. 27 2012 to fit the SPI scheme of the 
 ASIAA 5 GSps ADC chip. Modifications include:
 
 - changing SPI address width from 4 to 8
 - slowing down the SPI clock by factor of 2
 - removing first 8 bits of data shift register
 
 */
module opb_adc5g_controller(
    input         OPB_Clk,
    input         OPB_Rst,
    output [0:31] Sl_DBus,
    output        Sl_errAck,
    output        Sl_retry,
    output        Sl_toutSup,
    output        Sl_xferAck,
    input  [0:31] OPB_ABus,
    input  [0:3]  OPB_BE,
    input  [0:31] OPB_DBus,
    input         OPB_RNW,
    input         OPB_select,
    input         OPB_seqAddr,

	  output        adc0_adc3wire_clk,
	  output        adc0_adc3wire_data,
	  input         adc0_adc3wire_data_o,
	  output        adc0_adc3wire_spi_rst,
	  output        adc0_modepin,
	  output        adc0_reset,
	  output        adc0_dcm_reset,
    output        adc0_psclk,
    output        adc0_psen,
    output        adc0_psincdec,
    input         adc0_psdone,
    input         adc0_clk,

	  output        adc1_adc3wire_clk,
	  output        adc1_adc3wire_data,
	  input         adc1_adc3wire_data_o,
	  output        adc1_adc3wire_spi_rst,
	  output        adc1_modepin,
	  output        adc1_reset,
	  output        adc1_dcm_reset,
    output        adc1_psclk,
    output        adc1_psen,
    output        adc1_psincdec,
    input         adc1_psdone,
    input         adc1_clk
  );
  parameter C_BASEADDR    = 32'h00000000;
  parameter C_HIGHADDR    = 32'h0000FFFF;
  parameter C_OPB_AWIDTH  = 32;
  parameter C_OPB_DWIDTH  = 32;
  parameter C_FAMILY      = "";

  /* TODO: implement AUTO configuration */
  parameter INTERLEAVED_0 = 0;
  parameter INTERLEAVED_1 = 0;
  parameter AUTOCONFIG_0  = 0;
  parameter AUTOCONFIG_1  = 0;

  /********* Global Signals *************/

  wire [15:0] adc0_read_data;
  wire [15:0] adc0_config_data;
  wire  [7:0] adc0_config_addr;
  wire        adc0_config_start;
  wire        adc0_config_done;

  wire [15:0] adc1_read_data;
  wire [15:0] adc1_config_data;
  wire  [7:0] adc1_config_addr;
  wire        adc1_config_start;
  wire        adc1_config_done;

  wire        adc0_reset_wire;
  wire        adc1_reset_wire;

  /************ OPB Logic ***************/

  wire addr_match = OPB_ABus >= C_BASEADDR && OPB_ABus <= C_HIGHADDR;
  wire [31:0] opb_addr = OPB_ABus - C_BASEADDR;

  reg opb_ack;

  /*** Registers ****/

  reg adc0_reset_reg;
  reg adc1_reset_reg;
  assign adc0_reset_wire = adc0_reset_reg;
  assign adc1_reset_wire = adc1_reset_reg;

  reg adc0_mmcm_psen_reg;
  reg adc0_mmcm_psincdec_reg;
  assign adc0_psen     = adc0_mmcm_psen_reg;
  assign adc0_psincdec = adc0_mmcm_psincdec_reg;
  assign adc0_psclk    = OPB_Clk;

  reg adc1_mmcm_psen_reg;
  reg adc1_mmcm_psincdec_reg;
  assign adc1_psen     = adc1_mmcm_psen_reg;
  assign adc1_psincdec = adc1_mmcm_psincdec_reg;
  assign adc1_psclk    = OPB_Clk;

  reg [15:0] adc0_read_data_reg;
  assign adc0_read_data = adc0_read_data_reg;
   
  reg [15:0] adc0_config_data_reg;
  reg  [7:0] adc0_config_addr_reg;
  reg        adc0_config_start_reg;
  assign adc0_config_data  = adc0_config_data_reg;
  assign adc0_config_addr  = adc0_config_addr_reg;
  assign adc0_config_start = adc0_config_start_reg;

  reg [15:0] adc1_read_data_reg;
  assign adc1_read_data = adc1_read_data_reg;
   
  reg [15:0] adc1_config_data_reg;
  reg  [7:0] adc1_config_addr_reg;
  reg        adc1_config_start_reg;
  assign adc1_config_data  = adc1_config_data_reg;
  assign adc1_config_addr  = adc1_config_addr_reg;
  assign adc1_config_start = adc1_config_start_reg;

  reg [31:0] opb_data_out;

  always @(posedge OPB_Clk) begin
    opb_ack <= 1'b0;

    adc0_reset_reg <= 1'b0;
    adc1_reset_reg <= 1'b0;

    adc0_mmcm_psen_reg <= 1'b0;
    adc1_mmcm_psen_reg <= 1'b0;

    adc0_config_start_reg <= 1'b0;
    adc1_config_start_reg <= 1'b0;

    if (OPB_Rst) begin
    end else begin
      if (addr_match && OPB_select && !opb_ack) begin
        //opb_ack <= 1'b1;
        if (!OPB_RNW) begin
          case (opb_addr[3:2])
            0:  begin
	      opb_ack <= 1'b1;
              if (OPB_BE[3]) begin
                adc0_reset_reg <= OPB_DBus[31];
                adc1_reset_reg <= OPB_DBus[30];
              end
              if (OPB_BE[1]) begin
                adc0_mmcm_psen_reg <= OPB_DBus[15];
                adc1_mmcm_psen_reg <= OPB_DBus[11];
                adc0_mmcm_psincdec_reg <= OPB_DBus[14];
                adc1_mmcm_psincdec_reg <= OPB_DBus[10];
              end
            end
            1:  begin
	      if (adc0_config_done) begin
		 opb_ack <= 1'b1;
		 if (OPB_BE[3]) begin
                    adc0_config_start_reg <= OPB_DBus[31];
		 end
		 if (OPB_BE[2]) begin
                    adc0_config_addr_reg <= OPB_DBus[16:23];
		 end
		 if (OPB_BE[1]) begin
                    adc0_config_data_reg[7:0] <= OPB_DBus[8:15];
		 end
		 if (OPB_BE[0]) begin
                    adc0_config_data_reg[15:8] <= OPB_DBus[0:7];
		 end
	      end
            end
            2:  begin
	      if (adc1_config_done) begin
		 opb_ack <= 1'b1;
		 if (OPB_BE[3]) begin
                    adc1_config_start_reg <= OPB_DBus[31];
		 end
		 if (OPB_BE[2]) begin
                    adc1_config_addr_reg <= OPB_DBus[16:23];
		 end
		 if (OPB_BE[1]) begin
                    adc1_config_data_reg[7:0] <= OPB_DBus[8:15];
		 end
		 if (OPB_BE[0]) begin
                    adc1_config_data_reg[15:8] <= OPB_DBus[0:7];
		 end
	      end
            end
            3:  begin
            end
          endcase
        end else begin // if (!OPB_RNW)
	  case (opb_addr[3:2])
	    0: begin
	       opb_ack <= 1'b1;
	       opb_data_out <= {2'b0, adc1_psdone, adc0_psdone, 4'b0, 2'b0, adc1_mmcm_psincdec_reg, adc1_mmcm_psen_reg, 2'b0, adc0_mmcm_psincdec_reg, adc0_mmcm_psen_reg, 16'b0};
	    end
	    1: begin
	       opb_ack <= adc0_config_done ? 1'b1 : 1'b0;
	       opb_data_out <= {adc0_read_data_reg[15:8], adc0_read_data_reg[7:0], adc0_config_addr_reg, 7'b0, adc0_config_done};
	    end
	    2: begin
	       opb_ack <= adc1_config_done ? 1'b1 : 1'b0;
	       opb_data_out <= {adc1_read_data_reg[15:8], adc1_read_data_reg[7:0], adc1_config_addr_reg, 7'b0, adc1_config_done};
	    end
	    3: begin
	       opb_ack <= 1'b1;
	       opb_data_out <= {32'b0};
	    end
	  endcase
	end
      end
    end
  end

  assign Sl_DBus     = Sl_xferAck ? opb_data_out : 32'b0;
  assign Sl_errAck   = 1'b0;
  assign Sl_retry    = 1'b0;
  assign Sl_toutSup  = 1'b0;
  assign Sl_xferAck  = opb_ack;

  /********* DCM Reset Gen *********/


  reg [7:0] adc0_reset_counter;
  reg [7:0] adc1_reset_counter;

  reg adc0_reset_iob;
  reg adc1_reset_iob;
  // synthesis attribute IOB of adc0_reset_iob is TRUE
  // synthesis attribute IOB of adc1_reset_iob is TRUE

  always @(posedge OPB_Clk) begin

    if (OPB_Rst) begin
      adc0_reset_counter <= {8{1'b1}};
      adc1_reset_counter <= {8{1'b1}};
      adc0_reset_iob <= 1'b1;
      adc1_reset_iob <= 1'b1;
    end else begin
      adc0_reset_iob <= adc0_reset_wire;
      adc1_reset_iob <= adc1_reset_wire;
      if (adc0_reset_counter) begin
        adc0_reset_counter <= adc0_reset_counter - 1;
      end
      if (adc1_reset_counter) begin
        adc1_reset_counter <= adc1_reset_counter - 1;
      end
      if (adc0_reset_wire) begin
        adc0_reset_counter <= {8{1'b1}};
      end
      if (adc1_reset_wire) begin
        adc1_reset_counter <= {8{1'b1}};
      end
    end
  end

  assign adc0_dcm_reset = adc0_reset_counter != 0;
  assign adc1_dcm_reset = adc1_reset_counter != 0;
  assign adc0_reset = adc0_reset_counter != 0;//adc0_reset_iob;
  assign adc1_reset = adc1_reset_counter != 0;//adc1_reset_iob;

  /********* ADC0 configuration state machine *********/

  wire clk0_falling;
  wire clk0_midhigh;
  wire clk0_prerise;
  wire clk0_en;

  localparam CONFIG_IDLE        = 0;
  localparam CONFIG_CLKWAIT     = 1;
  localparam CONFIG_READWAIT    = 2;
  localparam CONFIG_DATA_ADDR   = 3;
  localparam CONFIG_DATA_WRITE  = 4;
  localparam CONFIG_DATA_READ   = 5;
  localparam CONFIG_ALMOST_DONE = 6;
  localparam CONFIG_FINISH      = 7;

  reg [2:0] adc0_state;

  reg [15:0] adc0_read_data_shift;

  reg [23:0] adc0_config_data_shift;

  reg [4:0] adc0_config_progress;

  always @(posedge OPB_Clk) begin
    if (OPB_Rst) begin
      adc0_state <= CONFIG_IDLE;
    end else begin
      case (adc0_state)
        CONFIG_IDLE: begin
          if (adc0_config_start) begin
            adc0_state <= CONFIG_CLKWAIT;
	    adc0_read_data_shift <= 16'b0;
            adc0_config_data_shift <= {adc0_config_addr, adc0_config_data};
          end
        end
        CONFIG_CLKWAIT: begin
          if (clk0_falling) begin
            adc0_state <= CONFIG_DATA_ADDR;
            adc0_config_progress <= 0;
          end
        end 
        CONFIG_READWAIT: begin
          if (clk0_falling) begin
            adc0_state <= CONFIG_DATA_READ;
          end
        end 
        CONFIG_DATA_ADDR: begin
          if (clk0_falling) begin
            adc0_config_data_shift <= adc0_config_data_shift << 1;
            adc0_config_progress <= adc0_config_progress + 1;
            if (adc0_config_progress == 7) begin
	      if (adc0_config_addr[7] == 1) begin
		adc0_state <= CONFIG_DATA_WRITE;
	      end else begin
		adc0_state <= CONFIG_READWAIT;
	      end
            end
          end
        end
        CONFIG_DATA_WRITE: begin
          if (clk0_falling) begin
	    adc0_config_data_shift <= adc0_config_data_shift << 1;
            adc0_config_progress <= adc0_config_progress + 1;
	  end
	  if (clk0_midhigh) begin
            if (adc0_config_progress == 23) begin
	      adc0_state <= CONFIG_ALMOST_DONE;
	    end
          end
        end
        CONFIG_DATA_READ: begin
          if (clk0_prerise) begin
	    adc0_config_progress <= adc0_config_progress + 1;
            if (adc0_config_progress == 16) begin
	      adc0_state <= CONFIG_READWAIT;
	    end else begin
	      adc0_read_data_shift <= {adc0_read_data_shift[14:0], adc0_adc3wire_data_o};
	    end
	  end
	  if (clk0_midhigh) begin
	    if (adc0_config_progress == 25) begin
	      adc0_state <= CONFIG_ALMOST_DONE;
	    end
          end
        end
        CONFIG_ALMOST_DONE: begin
          if (clk0_prerise) begin
            adc0_state <= CONFIG_FINISH;
          end
        end
        CONFIG_FINISH: begin
          if (clk0_falling) begin
            adc0_state <= CONFIG_IDLE;
	    adc0_read_data_reg <= adc0_read_data_shift;
          end
        end
        default: begin
          adc0_state <= CONFIG_IDLE;
        end
      endcase
    end
  end

  assign adc0_config_done = adc0_state == CONFIG_IDLE;
  
  /* Clock Control */

  reg [4:0] clk0_counter;
  always @(posedge OPB_Clk) begin
    if (clk0_en) begin
      clk0_counter <= clk0_counter + 1;
    end else begin
      clk0_counter <= 5'b0;
    end
  end
  assign clk0_falling = clk0_counter == 5'b00000;
  assign clk0_midhigh = clk0_counter == 5'b11000;
  assign clk0_prerise = clk0_counter == 5'b01111;
  assign clk0_en   = adc0_state != CONFIG_IDLE;

  assign adc0_modepin         = !((adc0_state == CONFIG_DATA_ADDR) || (adc0_state == CONFIG_DATA_WRITE) || (adc0_state == CONFIG_DATA_READ) || (adc0_state == CONFIG_READWAIT));
  assign adc0_adc3wire_data   = adc0_config_data_shift[23];
  assign adc0_adc3wire_clk    = clk0_counter[4] && !(adc0_state == CONFIG_READWAIT) && !(adc0_state == CONFIG_FINISH);

  /********* ADC1 configuration state machine *********/

  localparam CONFIG_DATA       = 2;

  wire clk1_prefall;
  wire clk1_prerise;
  wire clk1_en;

  reg [1:0] adc1_state;

  reg [15:0] adc1_read_data_shift;

  reg [23:0] adc1_config_data_shift;

  reg [4:0] adc1_config_progress;

  always @(posedge OPB_Clk) begin
    if (OPB_Rst) begin
      adc1_state <= CONFIG_IDLE;
    end else begin
      case (adc1_state)
        CONFIG_IDLE: begin
          if (adc1_config_start) begin
            adc1_state <= CONFIG_CLKWAIT;
	    adc1_read_data_shift <= 16'b0;
            adc1_config_data_shift <= {adc1_config_addr, adc1_config_data};
          end
        end
        CONFIG_CLKWAIT: begin
          if (clk1_prefall) begin
            adc1_state <= CONFIG_DATA;
            adc1_config_progress <= 0;
          end
        end 
        CONFIG_DATA: begin
          if (clk1_prefall) begin
            adc1_config_data_shift <= adc1_config_data_shift << 1;
            adc1_config_progress <= adc1_config_progress + 1;
            if (adc1_config_progress == 23) begin
              adc1_state <= CONFIG_FINISH;
            end
          end
	  if (clk1_prerise && adc1_config_progress > 7) begin
	    adc1_read_data_shift <= {adc1_read_data_shift[14:0], adc1_adc3wire_data_o};
	  end
        end
        CONFIG_FINISH: begin
          if (clk1_prefall) begin
            adc1_state <= CONFIG_IDLE;
	    adc1_read_data_reg <= adc1_read_data_shift;
          end
        end
        default: begin
          adc1_state <= CONFIG_IDLE;
        end
      endcase
    end
  end

  assign adc1_config_done = adc1_state == CONFIG_IDLE;

  /* Clock Control */

  reg [4:0] clk1_counter;
  always @(posedge OPB_Clk) begin
    if (clk1_en) begin
      clk1_counter <= clk1_counter + 1;
    end else begin
      clk1_counter <= 5'b0;
    end
  end
  assign clk1_prefall = clk1_counter == 5'b11111;
  assign clk1_prerise = clk1_counter == 5'b00000;
  assign clk1_en   = adc1_state != CONFIG_IDLE;

  assign adc1_modepin         = adc1_state == CONFIG_DATA;
  assign adc1_adc3wire_data   = adc1_config_data_shift[23];
  assign adc1_adc3wire_clk    = clk0_counter[4];

endmodule

xps_lib/XPS_ROACH2_base/pcores/opb_adc5g_controller_v1_00_a/tb/hdl/TB_opb_adc5g_controller.v
`timescale 1ns/10ps

`define SIMLENGTH 40000
`define SYS_CLK_PERIOD 4

module TB_opb_adc5g_controller();

   wire sys_rst;
   wire sys_clk;

   /***************** DUT ***************/
   wire OPB_Clk;
   wire OPB_Rst;
   wire [0:31] Sl_DBus;
   wire        Sl_errAck;
   wire        Sl_retry;
   wire        Sl_toutSup;
   wire        Sl_xferAck;
   wire [0:31] OPB_ABus;
   wire [0:3]  OPB_BE;
   wire [0:31] OPB_DBus;
   wire        OPB_RNW;
   wire        OPB_select;
   wire        OPB_seqAddr;

   wire        adc0_adc3wire_clk;
   wire        adc0_adc3wire_data;
   wire        adc0_adc3wire_data_o;
   wire        adc0_adc3wire_spi_rst;
   wire        adc0_modepin;
   wire        adc0_reset;
   wire        adc0_dcm_reset;
   wire        adc0_psclk;
   wire        adc0_psen;
   wire        adc0_psincdec;
   wire        adc0_psdone;
   wire        adc0_clk;

   wire        adc1_adc3wire_clk;
   wire        adc1_adc3wire_data;
   wire        adc1_adc3wire_data_o;
   wire        adc1_adc3wire_spi_rst;
   wire        adc1_modepin;
   wire        adc1_reset;
   wire        adc1_dcm_reset;
   wire        adc1_psclk;
   wire        adc1_psen;
   wire        adc1_psincdec;
   wire        adc1_psdone;
   wire        adc1_clk;

   opb_adc5g_controller opb_adc5g_controller_inst(
						  .OPB_Clk(OPB_Clk),
						  .OPB_Rst(OPB_Rst),
						  .Sl_DBus(Sl_DBus),
						  .Sl_errAck(Sl_errAck),
						  .Sl_retry(Sl_retry),
						  .Sl_toutSup(Sl_toutSup),
						  .Sl_xferAck(Sl_xferAck),
						  .OPB_ABus(OPB_ABus),
						  .OPB_BE(OPB_BE),
						  .OPB_DBus(OPB_DBus),
						  .OPB_RNW(OPB_RNW),
						  .OPB_select(OPB_select),
						  .OPB_seqAddr(OPB_seqAddr),
						  .adc0_adc3wire_clk(adc0_adc3wire_clk),
						  .adc0_adc3wire_data(adc0_adc3wire_data),
						  .adc0_adc3wire_data_o(adc0_adc3wire_data_o),
						  .adc0_modepin(adc0_modepin),
						  .adc0_reset(adc0_reset),
						  .adc0_dcm_reset(adc0_dcm_reset),
						  .adc0_psclk(adc0_psclk),
						  .adc0_psen(adc0_psen),
						  .adc0_psincdec(adc0_psincdec),
						  .adc0_psdone(adc0_psdone),
						  .adc0_clk(adc0_clk),
						  .adc1_adc3wire_clk(adc1_adc3wire_clk),
						  .adc1_adc3wire_data(adc1_adc3wire_data),
						  .adc1_adc3wire_data_o(adc1_adc3wire_data_o),
						  .adc1_modepin(adc1_modepin),
						  .adc1_reset(adc1_reset),
						  .adc1_dcm_reset(adc1_dcm_reset),
						  .adc1_psclk(adc1_psclk),
						  .adc1_psen(adc1_psen),
						  .adc1_psincdec(adc1_psincdec),
						  .adc1_psdone(adc1_psdone),
						  .adc1_clk(adc1_clk)
						  );

   /****** System Signal generations ******/
   reg [31:0]  sys_clk_counter;

   reg 	       reset;
   assign sys_rst = reset;

   initial begin
      $dumpvars;
      sys_clk_counter <= 32'b0;

      reset <= 1'b1;
      #20
	reset <= 1'b0;
`ifdef DEBUG
      $display("sys: reset cleared");
`endif
      #`SIMLENGTH
	$display("FAILED: system timeout");
      $finish;
   end

   assign sys_clk = sys_clk_counter < ((`SYS_CLK_PERIOD) / 2);

   always begin
      #1 sys_clk_counter <= (sys_clk_counter == `SYS_CLK_PERIOD - 1 ? 32'b0 : sys_clk_counter + 1);
   end

   assign OPB_Clk = sys_clk;
   assign OPB_Rst = sys_rst;

   reg [31:0] opb_data;
   reg [3:0]  opb_be;
   reg        opb_select;
   reg [31:0] opb_addr;
   reg        opb_rnw;

   reg [31:0] progress;

   always @(posedge sys_clk) begin
      if (sys_rst) begin
	 progress   <= 32'b0;
	 opb_select <= 0;
      end else begin
	 case (progress)
           0: begin
              opb_data <= 32'b11;
              opb_rnw  <= 0;
              opb_addr <= 0;
              opb_be   <= 4'b0001;
              opb_select <= 1'b1;
              progress <= 1;
           end
           1: begin
              if (Sl_xferAck) begin
		 opb_data <= {16'h03c8, 8'h81, 8'b1};
		 opb_addr <= 4;
		 opb_be   <= 4'b1111;
		 opb_rnw  <= 0;
		 opb_select <= 1'b1;
		 progress <= 2;
              end
           end
           2: begin
              if (Sl_xferAck) begin
		 opb_data <= {16'h03c8, 8'h01, 8'b1};
		 opb_addr <= 4;
		 opb_be   <= 4'b1111;
		 opb_rnw  <= 0;
		 opb_select <= 1'b1;
		 progress <= 3;
              end
           end
           3: begin
              if (Sl_xferAck) begin
		 opb_data <= 32'b0;
		 opb_addr <= 4;
		 opb_be   <= 4'b1111;
		 opb_rnw  <= 1;
		 opb_select <= 1'b1;
		 progress <= 4;
              end
           end
           4: begin
              if (Sl_xferAck) begin
		 opb_select <= 1'b0;
              end
           end
	 endcase
      end
   end 

   assign OPB_ABus   = opb_addr;
   assign OPB_BE     = opb_be;
   assign OPB_DBus   = opb_data;
   assign OPB_RNW    = opb_rnw;
   assign OPB_select = opb_select;

   reg [4:0] config0_cntr;
   initial begin
      config0_cntr <= 0;
   end

   reg [23:0] config0_data;
   reg 	      config0_data_o;
   reg 	      config0_reading;
   reg [15:0] config0_data_o_shift;

   assign adc0_adc3wire_data_o = config0_data_o;

   always @(posedge adc0_adc3wire_clk) begin
      if (sys_rst) begin
      end else begin
	 if (adc0_modepin === 0) begin
            config0_data[23-config0_cntr] <= adc0_adc3wire_data;
            config0_cntr <= config0_cntr + 1;
	    if (config0_cntr == 7) begin
	       if (config0_data[23] == 0) begin
		  config0_reading <= 1'b1;
	       end
	    end
            if (config0_cntr == 23) begin
	       config0_cntr <= 0;
	       config0_reading <= 1'b0;
               #10
			      $display("adc0_conf: %x", config0_data);
               if (config0_data === {8'h81, 16'h03c8}) begin
               end else begin
		  $display("FAILED @(%x): adc0 mismatch - got = %x, expected = %x", progress, config0_data, {8'h81, 16'h03c8});
               end
            end
	 end // if (adc0_modepin === 0)
      end
   end // always @ (posedge adc0_adc3wire_clk)

   always @(negedge adc0_adc3wire_clk) begin
      if (sys_rst) begin
	 config0_data_o <= 1'b0;
	 config0_data_o_shift <= 16'h03c8;
      end else begin
	 if (config0_reading) begin
	    config0_data_o <= config0_data_o_shift[15];
	    config0_data_o_shift <= config0_data_o_shift << 1;
	 end
      end
   end

   // reg [4:0] config1_cntr;
   // initial begin
   //    config1_cntr <= 0;
   // end

   // reg[23:0] config1_data;

   // always @(posedge adc1_adc3wire_clk) begin
   //    if (sys_rst) begin
   //    end else begin
   // 	 if (adc1_modepin === 0) begin
   //          config1_data[23 - config1_cntr] <= adc1_adc3wire_data;
   //          config1_cntr <= config1_cntr + 1;
   //          if (config1_cntr == 23) begin
   //             #20
   // 			      $display("adc1_conf: %x", config1_data);
   //             if (config1_data === {8'b1, 8'h81, 16'h03c8}) begin
   // 		  $display("PASSED");
   //             end else begin
   // 		  $display("FAILED: adc1 mismatch - got = %x, expected = %x", config1_data, {8'b1, 8'h81, 16'h03c8});
   //             end
   //             #1000 $finish;
   //          end
   // 	 end
   //    end
   // end

   
endmodule

xps_lib/XPS_ROACH2_base/pcores/opb_adc5g_controller_v1_00_a/tb/dump.vcd
$date
	Thu Mar  1 10:45:19 2012
$end
$version
	Icarus Verilog
$end
$timescale
	10ps
$end
$scope module TB_opb_adc5g_controller $end
$var wire 32 ! OPB_ABus [0:31] $end
$var wire 4 " OPB_BE [0:3] $end
$var wire 1 # OPB_Clk $end
$var wire 32 $ OPB_DBus [0:31] $end
$var wire 1 % OPB_RNW $end
$var wire 1 & OPB_Rst $end
$var wire 1 ' OPB_select $end
$var wire 1 ( OPB_seqAddr $end
$var wire 32 ) Sl_DBus [0:31] $end
$var wire 1 * Sl_errAck $end
$var wire 1 + Sl_retry $end
$var wire 1 , Sl_toutSup $end
$var wire 1 - Sl_xferAck $end
$var wire 1 . adc0_adc3wire_clk $end
$var wire 1 / adc0_adc3wire_data $end
$var wire 1 0 adc0_adc3wire_data_o $end
$var wire 1 1 adc0_clk $end
$var wire 1 2 adc0_dcm_reset $end
$var wire 1 3 adc0_modepin $end
$var wire 1 4 adc0_psclk $end
$var wire 1 5 adc0_psdone $end
$var wire 1 6 adc0_psen $end
$var wire 1 7 adc0_psincdec $end
$var wire 1 8 adc0_reset $end
$var wire 1 9 adc1_adc3wire_clk $end
$var wire 1 : adc1_adc3wire_data $end
$var wire 1 ; adc1_adc3wire_data_o $end
$var wire 1 < adc1_clk $end
$var wire 1 = adc1_dcm_reset $end
$var wire 1 > adc1_modepin $end
$var wire 1 ? adc1_psclk $end
$var wire 1 @ adc1_psdone $end
$var wire 1 A adc1_psen $end
$var wire 1 B adc1_psincdec $end
$var wire 1 C adc1_reset $end
$var wire 1 D sys_clk $end
$var wire 1 E sys_rst $end
$var reg 5 F config0_cntr [4:0] $end
$var reg 24 G config0_data [23:0] $end
$var reg 1 H config0_data_o $end
$var reg 16 I config0_data_o_shift [15:0] $end
$var reg 1 J config0_reading $end
$var reg 32 K opb_addr [31:0] $end
$var reg 4 L opb_be [3:0] $end
$var reg 32 M opb_data [31:0] $end
$var reg 1 N opb_rnw $end
$var reg 1 O opb_select $end
$var reg 32 P progress [31:0] $end
$var reg 1 Q reset $end
$var reg 32 R sys_clk_counter [31:0] $end
$scope module opb_adc5g_controller_inst $end
$var wire 32 S OPB_ABus [0:31] $end
$var wire 4 T OPB_BE [0:3] $end
$var wire 1 # OPB_Clk $end
$var wire 32 U OPB_DBus [0:31] $end
$var wire 1 % OPB_RNW $end
$var wire 1 & OPB_Rst $end
$var wire 1 ' OPB_select $end
$var wire 1 ( OPB_seqAddr $end
$var wire 32 V Sl_DBus [0:31] $end
$var wire 1 * Sl_errAck $end
$var wire 1 + Sl_retry $end
$var wire 1 , Sl_toutSup $end
$var wire 1 - Sl_xferAck $end
$var wire 1 . adc0_adc3wire_clk $end
$var wire 1 / adc0_adc3wire_data $end
$var wire 1 0 adc0_adc3wire_data_o $end
$var wire 1 W adc0_adc3wire_spi_rst $end
$var wire 1 1 adc0_clk $end
$var wire 8 X adc0_config_addr [7:0] $end
$var wire 16 Y adc0_config_data [15:0] $end
$var wire 1 Z adc0_config_done $end
$var wire 1 [ adc0_config_start $end
$var wire 1 2 adc0_dcm_reset $end
$var wire 1 3 adc0_modepin $end
$var wire 1 4 adc0_psclk $end
$var wire 1 5 adc0_psdone $end
$var wire 1 6 adc0_psen $end
$var wire 1 7 adc0_psincdec $end
$var wire 16 \ adc0_read_data [15:0] $end
$var wire 1 8 adc0_reset $end
$var wire 1 ] adc0_reset_wire $end
$var wire 1 9 adc1_adc3wire_clk $end
$var wire 1 : adc1_adc3wire_data $end
$var wire 1 ; adc1_adc3wire_data_o $end
$var wire 1 ^ adc1_adc3wire_spi_rst $end
$var wire 1 < adc1_clk $end
$var wire 8 _ adc1_config_addr [7:0] $end
$var wire 16 ` adc1_config_data [15:0] $end
$var wire 1 a adc1_config_done $end
$var wire 1 b adc1_config_start $end
$var wire 1 = adc1_dcm_reset $end
$var wire 1 > adc1_modepin $end
$var wire 1 ? adc1_psclk $end
$var wire 1 @ adc1_psdone $end
$var wire 1 A adc1_psen $end
$var wire 1 B adc1_psincdec $end
$var wire 16 c adc1_read_data [15:0] $end
$var wire 1 C adc1_reset $end
$var wire 1 d adc1_reset_wire $end
$var wire 1 e addr_match $end
$var wire 1 f clk0_en $end
$var wire 1 g clk0_falling $end
$var wire 1 h clk0_midhigh $end
$var wire 1 i clk0_prerise $end
$var wire 1 j clk1_en $end
$var wire 1 k clk1_prefall $end
$var wire 1 l clk1_prerise $end
$var wire 32 m opb_addr [31:0] $end
$var reg 8 n adc0_config_addr_reg [7:0] $end
$var reg 16 o adc0_config_data_reg [15:0] $end
$var reg 24 p adc0_config_data_shift [23:0] $end
$var reg 5 q adc0_config_progress [4:0] $end
$var reg 1 r adc0_config_start_reg $end
$var reg 1 s adc0_mmcm_psen_reg $end
$var reg 1 t adc0_mmcm_psincdec_reg $end
$var reg 16 u adc0_read_data_reg [15:0] $end
$var reg 16 v adc0_read_data_shift [15:0] $end
$var reg 8 w adc0_reset_counter [7:0] $end
$var reg 1 x adc0_reset_iob $end
$var reg 1 y adc0_reset_reg $end
$var reg 3 z adc0_state [2:0] $end
$var reg 8 { adc1_config_addr_reg [7:0] $end
$var reg 16 | adc1_config_data_reg [15:0] $end
$var reg 24 } adc1_config_data_shift [23:0] $end
$var reg 5 ~ adc1_config_progress [4:0] $end
$var reg 1 !" adc1_config_start_reg $end
$var reg 1 "" adc1_mmcm_psen_reg $end
$var reg 1 #" adc1_mmcm_psincdec_reg $end
$var reg 16 $" adc1_read_data_reg [15:0] $end
$var reg 16 %" adc1_read_data_shift [15:0] $end
$var reg 8 &" adc1_reset_counter [7:0] $end
$var reg 1 '" adc1_reset_iob $end
$var reg 1 (" adc1_reset_reg $end
$var reg 2 )" adc1_state [1:0] $end
$var reg 5 *" clk0_counter [4:0] $end
$var reg 5 +" clk1_counter [4:0] $end
$var reg 1 ," opb_ack $end
$var reg 32 -" opb_data_out [31:0] $end
$upscope $end
$upscope $end
$enddefinitions $end
#0
$dumpvars
bx -"
0,"
b0 +"
b0 *"
b0 )"
0("
1'"
b11111111 &"
bx %"
bx $"
x#"
0""
0!"
bx ~
bx }
bx |
bx {
b0 z
0y
1x
b11111111 w
bx v
bx u
xt
0s
0r
bx q
bx p
bx o
bx n
bx m
1l
0k
0j
0i
0h
1g
0f
xe
0d
bx c
0b
1a
bx `
bx _
z^
0]
bx \
0[
1Z
bx Y
bx X
zW
b0 V
bx U
bx T
bx S
b0 R
1Q
b0 P
0O
xN
bx M
bx L
bx K
xJ
b1111001000 I
0H
bx G
b0 F
1E
1D
1C
xB
0A
z@
1?
0>
1=
z<
z;
x:
09
18
x7
06
z5
14
13
12
z1
00
x/
0.
0-
0,
0+
0*
b0 )
z(
0'
1&
x%
bx $
1#
bx "
bx !
$end
#100
b1 R
#200
b10 R
0D
0#
04
0?
#300
b11 R
#400
b0 R
1D
1#
14
1?
#500
b1 R
#600
b10 R
0D
0#
04
0?
#700
b11 R
#800
b0 R
1D
1#
14
1?
#900
b1 R
#1000
b10 R
0D
0#
04
0?
#1100
b11 R
#1200
b0 R
1D
1#
14
1?
#1300
b1 R
#1400
b10 R
0D
0#
04
0?
#1500
b11 R
#1600
b0 R
1D
1#
14
1?
#1700
b1 R
#1800
b10 R
0D
0#
04
0?
#1900
b11 R
#2000
1e
b0 m
b1 P
1O
1'
b1 L
b1 "
b1 T
b0 K
b0 !
b0 S
0N
0%
b11 M
b11 $
b11 U
b11111110 &"
b11111110 w
0'"
0x
b0 R
1D
1#
14
1?
0Q
0E
0&
#2100
b1 R
#2200
b10 R
0D
0#
04
0?
#2300
b11 R
#2400
bx )
bx V
1("
1d
1y
1]
1,"
1-
b11111101 &"
b11111101 w
b0 R
1D
1#
14
1?
#2500
b1 R
#2600
b10 R
0D
0#
04
0?
#2700
b11 R
#2800
b100 m
b0 )
b0 V
b10 P
b1111 L
b1111 "
b1111 T
b100 K
b100 !
b100 S
b11110010001000000100000001 M
b11110010001000000100000001 $
b11110010001000000100000001 U
b11111111 &"
b11111111 w
1'"
1x
0("
0d
0y
0]
0,"
0-
b0 R
1D
1#
14
1?
#2900
b1 R
#3000
b10 R
0D
0#
04
0?
#3100
b11 R
#3200
bx )
bx V
b1111001000 o
b1111001000 Y
b10000001 n
b10000001 X
1r
1[
1,"
1-
b11111110 &"
b11111110 w
0'"
0x
b0 R
1D
1#
14
1?
#3300
b1 R
#3400
b10 R
0D
0#
04
0?
#3500
b11 R
